differential_transformer/__init__.py
differential_transformer/main.py
differential_transformer-0.0.3.dist-info/LICENSE
differential_transformer-0.0.3.dist-info/METADATA
differential_transformer-0.0.3.dist-info/WHEEL
differential_transformer-0.0.3.dist-info/RECORD
